stremio_api/__init__.py
stremio_api/client.py
stremio_api/models.py
stremio_api-0.1.0.dist-info/METADATA
stremio_api-0.1.0.dist-info/WHEEL
stremio_api-0.1.0.dist-info/top_level.txt
stremio_api-0.1.0.dist-info/RECORD
