Metadata-Version: 2.4
Name: stremio-api
Version: 0.1.0
Summary: A Python wrapper for the Stremio API
Author: abovecolin
Project-URL: Homepage, https://github.com/abovecolin/stremio-py
Project-URL: Bug Tracker, https://github.com/abovecolin/stremio-py/issues
Keywords: stremio,api,wrapper,media
Classifier: Programming Language :: Python :: 3
Classifier: License :: OSI Approved :: MIT License
Classifier: Operating System :: OS Independent
Classifier: Development Status :: 4 - Beta
Classifier: Intended Audience :: Developers
Requires-Python: >=3.9
Requires-Dist: httpx>=0.24.0
Requires-Dist: pydantic>=2.0.0
Provides-Extra: dev
Requires-Dist: pytest; extra == "dev"
Requires-Dist: pytest-asyncio; extra == "dev"
